flask_mongokat.py
setup.py
flask_mongokat.egg-info/PKG-INFO
flask_mongokat.egg-info/SOURCES.txt
flask_mongokat.egg-info/dependency_links.txt
flask_mongokat.egg-info/not-zip-safe
flask_mongokat.egg-info/requires.txt
flask_mongokat.egg-info/top_level.txt