Metadata-Version: 1.0
Name: flask-mongokat
Version: 1.0
Summary: Basic mongokat extension
Home-page: https://github.com/FranciscoCarbonell/flask-mongokat
Author: Francisco Carbonell
Author-email: francabezo@gmail.com
License: MIT
Platform: any
